configconfig/__init__.py
configconfig/autoconfig.py
configconfig/configvar.py
configconfig/metaclass.py
configconfig/parser.py
configconfig/py.typed
configconfig/testing.py
configconfig/utils.py
configconfig/validator.py
configconfig-0.6.2.dist-info/LICENSE
configconfig-0.6.2.dist-info/METADATA
configconfig-0.6.2.dist-info/WHEEL
configconfig-0.6.2.dist-info/entry_points.txt
configconfig-0.6.2.dist-info/RECORD
