Metadata-Version: 2.1
Name: configconfig
Version: 0.6.2
Summary: Load and validate YAML configuration files.
Author-email: Dominic Davis-Foster <dominic@davis-foster.co.uk>
License: MIT
Keywords: configuration,yaml
Home-page: https://github.com/repo-helper/configconfig
Project-URL: Issue Tracker, https://github.com/repo-helper/configconfig/issues
Project-URL: Source Code, https://github.com/repo-helper/configconfig
Project-URL: Documentation, https://configconfig.readthedocs.io/en/latest
Platform: Windows
Platform: macOS
Platform: Linux
Classifier: Development Status :: 4 - Beta
Classifier: Intended Audience :: Developers
Classifier: License :: OSI Approved :: MIT License
Classifier: Operating System :: OS Independent
Classifier: Programming Language :: Python
Classifier: Programming Language :: Python :: 3 :: Only
Classifier: Programming Language :: Python :: 3.6
Classifier: Programming Language :: Python :: 3.7
Classifier: Programming Language :: Python :: 3.8
Classifier: Programming Language :: Python :: 3.9
Classifier: Programming Language :: Python :: 3.10
Classifier: Programming Language :: Python :: 3.11
Classifier: Programming Language :: Python :: Implementation :: CPython
Classifier: Topic :: Software Development :: Libraries :: Python Modules
Classifier: Typing :: Typed
Requires-Python: >=3.6
Requires-Dist: domdf-python-tools>=0.10.0
Requires-Dist: jsonschema>=3.2.0
Requires-Dist: ruamel.yaml>=0.16.12
Requires-Dist: typing-extensions>=3.7.4.3
Requires-Dist: typing-inspect>=0.6.0
Requires-Dist: docutils; extra == 'sphinx'
Requires-Dist: sphinx<3.4.0,>=3.0.3; extra == 'sphinx'
Requires-Dist: sphinx-toolbox; extra == 'sphinx'
Requires-Dist: pytest; extra == 'testing'
Requires-Dist: docutils; extra == 'all'
Requires-Dist: pytest; extra == 'all'
Requires-Dist: sphinx<3.4.0,>=3.0.3; extra == 'all'
Requires-Dist: sphinx-toolbox; extra == 'all'
Provides-Extra: sphinx
Provides-Extra: testing
Provides-Extra: all
